pepython/__init__.py
pepython/common.py
pepython/entrypoints.py
pepython/task_def.py
pepython-0.2.5.dist-info/LICENSE
pepython-0.2.5.dist-info/METADATA
pepython-0.2.5.dist-info/WHEEL
pepython-0.2.5.dist-info/entry_points.txt
pepython-0.2.5.dist-info/top_level.txt
pepython-0.2.5.dist-info/RECORD
