Metadata-Version: 2.1
Name: pepython
Version: 0.2.5
Summary: Simple task automation for projects.
Home-page: https://github.com/nandilugio/pepython
Author: Fernando Stecconi
Author-email: nandilugio@gmail.com
License: MIT
Classifier: Programming Language :: Python :: 3
Classifier: License :: OSI Approved :: MIT License
Classifier: Operating System :: OS Independent
License-File: LICENSE
Requires-Dist: pyyaml
